{"1": {"becameSuitTime": 1529695640.752, "savedBy": null, "track": "l", "numFloors": 2, "difficulty": 4, "state": "suit", "block": 1}, "3": {"becameSuitTime": 1529696023.341, "savedBy": null, "track": "s", "numFloors": 4, "difficulty": 6, "state": "suit", "block": 3}, "4": {"becameSuitTime": 1529695615.78, "savedBy": null, "track": "s", "numFloors": 5, "difficulty": 6, "state": "suit", "block": 4}, "5": {"becameSuitTime": 1529695890.701, "savedBy": null, "track": "s", "numFloors": 4, "difficulty": 4, "state": "suit", "block": 5}}